{
    "id":
    "MODULE_SPACEFUEL_PRODUCTION",
    "type":
    "Production",
    "factions": ["FACTION_ARGON"],
    "resources": [{
        "id": "PRODUCT_ENERGY_CELLS",
        "amount": 300
    }, {
        "id": "PRODUCT_WATER",
        "amount": 750
    }, {
        "id": "PRODUCT_WHEAT",
        "amount": 600
    }],
    "products": [{
        "id": "PRODUCT_SPACEFUEL",
        "amount": 900
    }],
    "turret":
    12,
    "max_employee_num":
    150,
    "max_efficiency":
    1.38,
    "name": {
        "en_US": "Spacefuel Production",
        "zh_CN": "太空燃料产线"
    }
}
